{"cameraMode":{"drawMode":0,"name":"Shaded","section":"Shading Mode"},"sceneLighting":false,"audioPlay":false,"sceneViewState":{"m_AlwaysRefresh":false,"showFog":true,"showSkybox":false,"showFlares":true,"showImageEffects":true,"showParticleSystems":true,"showVisualEffectGraphs":true,"m_FxEnabled":true},"in2DMode":false,"pivot":{"x":-36.480743408203128,"y":16.783174514770509,"z":-4.7284088134765629},"rotation":{"x":0.11691057682037354,"y":-0.27049413323402407,"z":0.03311219811439514,"w":0.9550259709358215},"size":19.55557632446289,"orthographic":false}